clover_gui/__init__.py
clover_gui/__main__.py
clover_gui/__utils__.py
clover_gui/configuration.py
clover_gui/load_location.py
clover_gui/main_menu.py
clover_gui/new_location.py
clover_gui/post_run.py
clover_gui/preferences.py
clover_gui/running.py
clover_gui/scenario.py
clover_gui/splash_screen.py
clover_gui/v0.1_main.py
clover_gui/data/images/100x
clover_gui/data/images/100x-0
clover_gui/data/images/QMark_hovered.png
clover_gui/data/images/QMark_unhovered.png
clover_gui/data/images/Qmark_hovered.png
clover_gui/data/images/Qmark_unhovered.png
clover_gui/data/images/back_arrow.png
clover_gui/data/images/battery_gui_deselected.png
clover_gui/data/images/battery_gui_disabled.png
clover_gui/data/images/battery_gui_selected.png
clover_gui/data/images/clean_water_gui_selected_filled.png
clover_gui/data/images/clean_water_gui_selected_outline.png
clover_gui/data/images/clover_logo.png
clover_gui/data/images/clover_splash_screen.png
clover_gui/data/images/clover_splash_screen_5_2.png
clover_gui/data/images/clover_splash_screen_5_2_beta.png
clover_gui/data/images/commercial_gui_deselected.png
clover_gui/data/images/commercial_gui_disabled.png
clover_gui/data/images/commercial_gui_selected.png
clover_gui/data/images/diesel_gui_deselected.png
clover_gui/data/images/diesel_gui_disabled-0.png
clover_gui/data/images/diesel_gui_disabled-1.png
clover_gui/data/images/diesel_gui_disabled.png
clover_gui/data/images/diesel_gui_selected-0.png
clover_gui/data/images/diesel_gui_selected-1.png
clover_gui/data/images/diesel_gui_selected.png
clover_gui/data/images/domestic_gui_deselected.png
clover_gui/data/images/domestic_gui_disabled.png
clover_gui/data/images/domestic_gui_selected.png
clover_gui/data/images/electric_gui_deselected.png
clover_gui/data/images/electric_gui_selected_filled.png
clover_gui/data/images/electric_gui_selected_outline.png
clover_gui/data/images/forward_arrow.png
clover_gui/data/images/grid_gui_deselected.png
clover_gui/data/images/grid_gui_disabled.png
CLOVER_GUI-1.0.0b4.dist-info/LICENSE
CLOVER_GUI-1.0.0b4.dist-info/METADATA
CLOVER_GUI-1.0.0b4.dist-info/WHEEL
CLOVER_GUI-1.0.0b4.dist-info/entry_points.txt
CLOVER_GUI-1.0.0b4.dist-info/top_level.txt
CLOVER_GUI-1.0.0b4.dist-info/RECORD
