Metadata-Version: 2.1
Name: CLOVER-GUI
Version: 1.0.0b4
Summary: A graphical user interface for CLOVER
Home-page: https://github.com/CLOVER-energy/CLOVER-GUI
Author: Ben Winchester and Hamish Beath
Author-email: benedict.winchester@gmail.com,hamishbeath@outlook.com
Project-URL: Bug Tracker, https://github.com/CLOVER-energy/CLOVER-GUI/issues
Classifier: Programming Language :: Python :: 3.10
Classifier: License :: OSI Approved :: MIT License
Classifier: Operating System :: OS Independent
Requires-Python: >=3.10
License-File: LICENSE
Requires-Dist: clover-energy >=5.2.0b1
Requires-Dist: customtkinter >=5.2.0
Requires-Dist: cx-Freeze >=6.15.5
Requires-Dist: pandas >=1.2.3
Requires-Dist: PyYAML >=5.4.1
Requires-Dist: RangeSlider >=2021.7.4
Requires-Dist: seaborn >=0.11.1
Requires-Dist: ttkbootstrap >=1.10.1
